{
    "info": {
        "next": null,
        "prev": "./products2.json",
        "number": 3
    },
    "results": [
        {
            "id": 17,
            "nameProduct": "APSAFPOFPIfasf sas",
            "img": "https://acdn.mitiendanube.com/stores/001/990/174/products/la-1x1-1011-8b8b0da2ba906190cb16472876097245-320-0.webp",
            "price": 784.88,
            "stock": 10
        },
        {
            "id": 18,
            "nameProduct": "APSAFPOFPIfasf sas",
            "img": "https://acdn.mitiendanube.com/stores/001/990/174/products/la-1x1-1021-148a90fb3ed37c81ef16475202157675-320-0.webp",
            "price": 34.12,
            "stock": 5
        },
        {
            "id": 19,
            "nameProduct": "APSAFPOFPIfasf sas",
            "img": "https://acdn.mitiendanube.com/stores/001/990/174/products/la-1x1-271-bd3464a74a98b9132a16475220343247-320-0.webp",
            "price": 21.123,
            "stock": 15
        },
        {
            "id": 20,
            "nameProduct": "APSAFPOFPIfasf sas",
            "img": "https://acdn.mitiendanube.com/stores/001/990/174/products/la-1x1-1011-8b8b0da2ba906190cb16472876097245-320-0.webp",
            "price": 24.3,
            "stock": 8
        },
        {
            "id": 21,
            "nameProduct": "APSAFPOFPIfasf sas",
            "img": "https://acdn.mitiendanube.com/stores/001/990/174/products/la-1x1-1011-8b8b0da2ba906190cb16472876097245-320-0.webp",
            "price": 924.3,
            "stock": 3
        },
        {
            "id": 22,
            "nameProduct": "APSAFPOFPIfasf sas",
            "img": "https://acdn.mitiendanube.com/stores/001/990/174/products/la-1x1-1011-8b8b0da2ba906190cb16472876097245-320-0.webp",
            "price": 884.123,
            "stock": 9
        },
        {
            "id": 23,
            "nameProduct": "APSAFPOFPIfasf sas",
            "img": "https://acdn.mitiendanube.com/stores/001/990/174/products/la-1x1-1011-8b8b0da2ba906190cb16472876097245-320-0.webp",
            "price": 964.13,
            "stock": 12
        },
        {
            "id": 24,
            "nameProduct": "APSAFPOFPIfasf sas",
            "img": "https://acdn.mitiendanube.com/stores/001/990/174/products/la-1x1-1011-8b8b0da2ba906190cb16472876097245-320-0.webp",
            "price": 964.13,
            "stock": 12
        }
    ]
}
